MANIFEST.in
README.md
setup.cfg
setup.py
./fredhutch_batch_wrapper/__init__.py
./fredhutch_batch_wrapper/client.py
./fredhutch_batch_wrapper/godaddy.crt
fredhutch_batch_wrapper/__init__.py
fredhutch_batch_wrapper/client.py
fredhutch_batch_wrapper/godaddy.crt
fredhutch_batch_wrapper.egg-info/PKG-INFO
fredhutch_batch_wrapper.egg-info/SOURCES.txt
fredhutch_batch_wrapper.egg-info/dependency_links.txt
fredhutch_batch_wrapper.egg-info/requires.txt
fredhutch_batch_wrapper.egg-info/top_level.txt