Metadata-Version: 1.0
Name: fredhutch-batch-wrapper
Version: 0.8
Summary: Fred Hutch Wrapper for AWS Batch
Home-page: https://github.com/FredHutch/fredhutch_batch_wrapper
Author: Dan Tenenbaum
Author-email: dtenenba@fredhutch.org
License: MIT
Platform: UNKNOWN
